backup/__init__.py
backup/photo_backup.py
backup/utils/__init__.py
backup/utils/cache_utils.py
backup/utils/camera_overrides.py
backup/utils/file_delta.py
backup/utils/file_utils.py
backup/utils/inspect_exif.py
backup/utils/metadata_utils.py
backup/utils/path_utils.py
photonkit-0.2.1.dist-info/licenses/LICENSE
photonkit-0.2.1.dist-info/METADATA
photonkit-0.2.1.dist-info/WHEEL
photonkit-0.2.1.dist-info/entry_points.txt
photonkit-0.2.1.dist-info/top_level.txt
photonkit-0.2.1.dist-info/RECORD
