Metadata-Version: 2.4
Name: photonkit
Version: 0.2.1
Summary: PhotonKit -- A mildly opinionated toolkit for managing your camera photo collection
Author: Rahul Singh
License: MIT
Classifier: License :: OSI Approved :: MIT License
Classifier: Operating System :: MacOS :: MacOS X
Classifier: Programming Language :: Python :: 3
Classifier: Environment :: Console
Classifier: Topic :: Utilities
Requires-Python: >=3.8
License-File: LICENSE
Dynamic: author
Dynamic: classifier
Dynamic: description
Dynamic: description-content-type
Dynamic: license
Dynamic: license-file
Dynamic: requires-python
Dynamic: summary
